{
  "_format": "hh-sol-cache-2",
  "files": {
    "/Users/sdax/Documents/Workspace/NFTMarketplace/node_modules/hardhat/console.sol": {
      "lastModificationDate": 1627150174316,
      "contentHash": "cc4777addd464ea56fa35b1c45df0591",
      "sourceName": "hardhat/console.sol",
      "solcConfig": {
        "version": "0.8.6",
        "settings": {
          "optimizer": {
            "enabled": true,
            "runs": 50
          },
          "outputSelection": {
            "*": {
              "*": [
                "abi",
                "evm.bytecode",
                "evm.deployedBytecode",
                "evm.methodIdentifiers",
                "metadata",
                "devdoc",
                "userdoc",
                "storageLayout",
                "evm.gasEstimates"
              ],
              "": [
                "ast"
              ]
            }
          },
          "metadata": {
            "useLiteralContent": true
          }
        }
      },
      "imports": [],
      "versionPragmas": [
        ">=0.4.22 <0.9.0"
      ],
      "artifacts": [
        "console"
      ]
    },
    "/Users/sdax/Documents/Workspace/NFTMarketplace/contracts/Ownable.sol": {
      "lastModificationDate": 1627190256016,
      "contentHash": "861bd565f12930ef31874c72e226092f",
      "sourceName": "contracts/Ownable.sol",
      "solcConfig": {
        "version": "0.8.6",
        "settings": {
          "optimizer": {
            "enabled": true,
            "runs": 50
          },
          "outputSelection": {
            "*": {
              "*": [
                "abi",
                "evm.bytecode",
                "evm.deployedBytecode",
                "evm.methodIdentifiers",
                "metadata",
                "devdoc",
                "userdoc",
                "storageLayout",
                "evm.gasEstimates"
              ],
              "": [
                "ast"
              ]
            }
          },
          "metadata": {
            "useLiteralContent": true
          }
        }
      },
      "imports": [],
      "versionPragmas": [
        "^0.8.0"
      ],
      "artifacts": [
        "Ownable"
      ]
    },
    "/Users/sdax/Documents/Workspace/NFTMarketplace/contracts/Address.sol": {
      "lastModificationDate": 1627228453391,
      "contentHash": "750b244702a16ef3d8e27714bf457403",
      "sourceName": "contracts/Address.sol",
      "solcConfig": {
        "version": "0.8.6",
        "settings": {
          "optimizer": {
            "enabled": true,
            "runs": 50
          },
          "outputSelection": {
            "*": {
              "*": [
                "abi",
                "evm.bytecode",
                "evm.deployedBytecode",
                "evm.methodIdentifiers",
                "metadata",
                "devdoc",
                "userdoc",
                "storageLayout",
                "evm.gasEstimates"
              ],
              "": [
                "ast"
              ]
            }
          },
          "metadata": {
            "useLiteralContent": true
          }
        }
      },
      "imports": [],
      "versionPragmas": [
        "^0.8.0"
      ],
      "artifacts": [
        "Address"
      ]
    },
    "/Users/sdax/Documents/Workspace/NFTMarketplace/contracts/NFTMarketplace.sol": {
      "lastModificationDate": 1627228372513,
      "contentHash": "7f1e75838683f14998299a8035c71eb9",
      "sourceName": "contracts/NFTMarketplace.sol",
      "solcConfig": {
        "version": "0.8.6",
        "settings": {
          "optimizer": {
            "enabled": true,
            "runs": 50
          },
          "outputSelection": {
            "*": {
              "*": [
                "abi",
                "evm.bytecode",
                "evm.deployedBytecode",
                "evm.methodIdentifiers",
                "metadata",
                "devdoc",
                "userdoc",
                "storageLayout",
                "evm.gasEstimates"
              ],
              "": [
                "ast"
              ]
            }
          },
          "metadata": {
            "useLiteralContent": true
          }
        }
      },
      "imports": [
        "./Address.sol",
        "./Ownable.sol",
        "./NFTMarketplaceStorage.sol"
      ],
      "versionPragmas": [
        "^0.8.0"
      ],
      "artifacts": [
        "NFTMarketplace"
      ]
    },
    "/Users/sdax/Documents/Workspace/NFTMarketplace/contracts/NFTMarketplaceStorage.sol": {
      "lastModificationDate": 1627228299194,
      "contentHash": "577d77af2459bc2f869ec07681f51ca9",
      "sourceName": "contracts/NFTMarketplaceStorage.sol",
      "solcConfig": {
        "version": "0.8.6",
        "settings": {
          "optimizer": {
            "enabled": true,
            "runs": 50
          },
          "outputSelection": {
            "*": {
              "*": [
                "abi",
                "evm.bytecode",
                "evm.deployedBytecode",
                "evm.methodIdentifiers",
                "metadata",
                "devdoc",
                "userdoc",
                "storageLayout",
                "evm.gasEstimates"
              ],
              "": [
                "ast"
              ]
            }
          },
          "metadata": {
            "useLiteralContent": true
          }
        }
      },
      "imports": [],
      "versionPragmas": [
        "^0.8.0"
      ],
      "artifacts": [
        "ERC20Interface",
        "ERC721Interface",
        "ERC721Verifiable",
        "NFTMarketplaceStorage"
      ]
    },
    "/Users/sdax/Documents/Workspace/NFTMarketplace/contracts/SafePaymentLibrary.sol": {
      "lastModificationDate": 1627199183124,
      "contentHash": "fc2aa6bc26b2ba4764be67a61a53e1a8",
      "sourceName": "contracts/SafePaymentLibrary.sol",
      "solcConfig": {
        "version": "0.8.6",
        "settings": {
          "optimizer": {
            "enabled": true,
            "runs": 50
          },
          "outputSelection": {
            "*": {
              "*": [
                "abi",
                "evm.bytecode",
                "evm.deployedBytecode",
                "evm.methodIdentifiers",
                "metadata",
                "devdoc",
                "userdoc",
                "storageLayout",
                "evm.gasEstimates"
              ],
              "": [
                "ast"
              ]
            }
          },
          "metadata": {
            "useLiteralContent": true
          }
        }
      },
      "imports": [
        "./PaymentTokenInterface.sol",
        "./Address.sol"
      ],
      "versionPragmas": [
        "^0.8.0"
      ],
      "artifacts": [
        "SafePaymentToken"
      ]
    },
    "/Users/sdax/Documents/Workspace/NFTMarketplace/contracts/PaymentTokenInterface.sol": {
      "lastModificationDate": 1627195686049,
      "contentHash": "c15fb199c88b6ac3b29594a9a4064a54",
      "sourceName": "contracts/PaymentTokenInterface.sol",
      "solcConfig": {
        "version": "0.8.6",
        "settings": {
          "optimizer": {
            "enabled": true,
            "runs": 50
          },
          "outputSelection": {
            "*": {
              "*": [
                "abi",
                "evm.bytecode",
                "evm.deployedBytecode",
                "evm.methodIdentifiers",
                "metadata",
                "devdoc",
                "userdoc",
                "storageLayout",
                "evm.gasEstimates"
              ],
              "": [
                "ast"
              ]
            }
          },
          "metadata": {
            "useLiteralContent": true
          }
        }
      },
      "imports": [],
      "versionPragmas": [
        "^0.8.0"
      ],
      "artifacts": [
        "PaymentTokenInterface"
      ]
    },
    "/Users/sdax/Documents/Workspace/NFTMarketplace/contracts/PaymentToken.sol": {
      "lastModificationDate": 1627198146776,
      "contentHash": "48c3f6df2a89da8740103fe4732fbfbd",
      "sourceName": "contracts/PaymentToken.sol",
      "solcConfig": {
        "version": "0.8.6",
        "settings": {
          "optimizer": {
            "enabled": true,
            "runs": 50
          },
          "outputSelection": {
            "*": {
              "*": [
                "abi",
                "evm.bytecode",
                "evm.deployedBytecode",
                "evm.methodIdentifiers",
                "metadata",
                "devdoc",
                "userdoc",
                "storageLayout",
                "evm.gasEstimates"
              ],
              "": [
                "ast"
              ]
            }
          },
          "metadata": {
            "useLiteralContent": true
          }
        }
      },
      "imports": [
        "./PaymentTokenInterface.sol"
      ],
      "versionPragmas": [
        "^0.8.0"
      ],
      "artifacts": [
        "PaymentToken"
      ]
    },
    "/Users/sdax/Documents/Workspace/NFTMarketplace/contracts/NFTToken.sol": {
      "lastModificationDate": 1627228952934,
      "contentHash": "25ef2a45bad9d60ae811b821de2dc389",
      "sourceName": "contracts/NFTToken.sol",
      "solcConfig": {
        "version": "0.8.6",
        "settings": {
          "optimizer": {
            "enabled": true,
            "runs": 50
          },
          "outputSelection": {
            "*": {
              "*": [
                "abi",
                "evm.bytecode",
                "evm.deployedBytecode",
                "evm.methodIdentifiers",
                "metadata",
                "devdoc",
                "userdoc",
                "storageLayout",
                "evm.gasEstimates"
              ],
              "": [
                "ast"
              ]
            }
          },
          "metadata": {
            "useLiteralContent": true
          }
        }
      },
      "imports": [
        "./NFTTokenInterface.sol",
        "./NFTReceiver.sol",
        "./NFTTokenMetadata.sol",
        "./InterfaceDetector.sol",
        "./Address.sol",
        "./Strings.sol"
      ],
      "versionPragmas": [
        "^0.8.0"
      ],
      "artifacts": [
        "NFTToken"
      ]
    },
    "/Users/sdax/Documents/Workspace/NFTMarketplace/contracts/NFTTokenInterface.sol": {
      "lastModificationDate": 1627227797303,
      "contentHash": "b12e53ad3decf4a4bb37c0929cc80b89",
      "sourceName": "contracts/NFTTokenInterface.sol",
      "solcConfig": {
        "version": "0.8.6",
        "settings": {
          "optimizer": {
            "enabled": true,
            "runs": 50
          },
          "outputSelection": {
            "*": {
              "*": [
                "abi",
                "evm.bytecode",
                "evm.deployedBytecode",
                "evm.methodIdentifiers",
                "metadata",
                "devdoc",
                "userdoc",
                "storageLayout",
                "evm.gasEstimates"
              ],
              "": [
                "ast"
              ]
            }
          },
          "metadata": {
            "useLiteralContent": true
          }
        }
      },
      "imports": [],
      "versionPragmas": [
        "^0.8.0"
      ],
      "artifacts": [
        "NFTTokenInterface"
      ]
    },
    "/Users/sdax/Documents/Workspace/NFTMarketplace/contracts/Strings.sol": {
      "lastModificationDate": 1627200559373,
      "contentHash": "d9acdb1d103397f02e0f8d0acd5f46ec",
      "sourceName": "contracts/Strings.sol",
      "solcConfig": {
        "version": "0.8.6",
        "settings": {
          "optimizer": {
            "enabled": true,
            "runs": 50
          },
          "outputSelection": {
            "*": {
              "*": [
                "abi",
                "evm.bytecode",
                "evm.deployedBytecode",
                "evm.methodIdentifiers",
                "metadata",
                "devdoc",
                "userdoc",
                "storageLayout",
                "evm.gasEstimates"
              ],
              "": [
                "ast"
              ]
            }
          },
          "metadata": {
            "useLiteralContent": true
          }
        }
      },
      "imports": [],
      "versionPragmas": [
        "^0.8.0"
      ],
      "artifacts": [
        "Strings"
      ]
    },
    "/Users/sdax/Documents/Workspace/NFTMarketplace/contracts/NFTReceiver.sol": {
      "lastModificationDate": 1627228410604,
      "contentHash": "eb910d2871f1fd23e6751b69c74f9304",
      "sourceName": "contracts/NFTReceiver.sol",
      "solcConfig": {
        "version": "0.8.6",
        "settings": {
          "optimizer": {
            "enabled": true,
            "runs": 50
          },
          "outputSelection": {
            "*": {
              "*": [
                "abi",
                "evm.bytecode",
                "evm.deployedBytecode",
                "evm.methodIdentifiers",
                "metadata",
                "devdoc",
                "userdoc",
                "storageLayout",
                "evm.gasEstimates"
              ],
              "": [
                "ast"
              ]
            }
          },
          "metadata": {
            "useLiteralContent": true
          }
        }
      },
      "imports": [],
      "versionPragmas": [
        "^0.8.0"
      ],
      "artifacts": [
        "NFTReceiver"
      ]
    },
    "/Users/sdax/Documents/Workspace/NFTMarketplace/contracts/NFTTokenMetadata.sol": {
      "lastModificationDate": 1627227416981,
      "contentHash": "6366a39eaf2960efe49f423b955d3d1e",
      "sourceName": "contracts/NFTTokenMetadata.sol",
      "solcConfig": {
        "version": "0.8.6",
        "settings": {
          "optimizer": {
            "enabled": true,
            "runs": 50
          },
          "outputSelection": {
            "*": {
              "*": [
                "abi",
                "evm.bytecode",
                "evm.deployedBytecode",
                "evm.methodIdentifiers",
                "metadata",
                "devdoc",
                "userdoc",
                "storageLayout",
                "evm.gasEstimates"
              ],
              "": [
                "ast"
              ]
            }
          },
          "metadata": {
            "useLiteralContent": true
          }
        }
      },
      "imports": [
        "./NFTTokenInterface.sol"
      ],
      "versionPragmas": [
        "^0.8.0"
      ],
      "artifacts": [
        "NFTTokenMetadata"
      ]
    },
    "/Users/sdax/Documents/Workspace/NFTMarketplace/contracts/InterfaceDetector.sol": {
      "lastModificationDate": 1627228610450,
      "contentHash": "4d41065086cd538ba6f3ec1a3361acb6",
      "sourceName": "contracts/InterfaceDetector.sol",
      "solcConfig": {
        "version": "0.8.6",
        "settings": {
          "optimizer": {
            "enabled": true,
            "runs": 50
          },
          "outputSelection": {
            "*": {
              "*": [
                "abi",
                "evm.bytecode",
                "evm.deployedBytecode",
                "evm.methodIdentifiers",
                "metadata",
                "devdoc",
                "userdoc",
                "storageLayout",
                "evm.gasEstimates"
              ],
              "": [
                "ast"
              ]
            }
          },
          "metadata": {
            "useLiteralContent": true
          }
        }
      },
      "imports": [
        "./InterfaceDetectorInterface.sol"
      ],
      "versionPragmas": [
        "^0.8.0"
      ],
      "artifacts": [
        "InterfaceDetector"
      ]
    },
    "/Users/sdax/Documents/Workspace/NFTMarketplace/contracts/InterfaceDetectorInterface.sol": {
      "lastModificationDate": 1627228603090,
      "contentHash": "af998f6d8f9db2e310b4ce1b44f44b9b",
      "sourceName": "contracts/InterfaceDetectorInterface.sol",
      "solcConfig": {
        "version": "0.8.6",
        "settings": {
          "optimizer": {
            "enabled": true,
            "runs": 50
          },
          "outputSelection": {
            "*": {
              "*": [
                "abi",
                "evm.bytecode",
                "evm.deployedBytecode",
                "evm.methodIdentifiers",
                "metadata",
                "devdoc",
                "userdoc",
                "storageLayout",
                "evm.gasEstimates"
              ],
              "": [
                "ast"
              ]
            }
          },
          "metadata": {
            "useLiteralContent": true
          }
        }
      },
      "imports": [],
      "versionPragmas": [
        "^0.8.0"
      ],
      "artifacts": [
        "InterfaceDetectorInterface"
      ]
    }
  }
}
